README.rst
setup.py
django_staticassets.egg-info/PKG-INFO
django_staticassets.egg-info/SOURCES.txt
django_staticassets.egg-info/dependency_links.txt
django_staticassets.egg-info/top_level.txt
staticassets/__init__.py
staticassets/exceptions.py
staticassets/filters.py
staticassets/finder.py
staticassets/handlers.py
staticassets/models.py
staticassets/settings.py
staticassets/storage.py
staticassets/utils.py
staticassets/views.py
staticassets/assets/__init__.py
staticassets/assets/attributes.py
staticassets/compilers/__init__.py
staticassets/compilers/base.py
staticassets/compilers/coffeescript.py
staticassets/compilers/jst.py
staticassets/compilers/less.py
staticassets/compilers/sass.py
staticassets/compilers/stylus.py
staticassets/compressors/__init__.py
staticassets/management/__init__.py
staticassets/management/commands/__init__.py
staticassets/management/commands/runserver.py
staticassets/processors/__init__.py
staticassets/processors/base.py
staticassets/processors/directive.py
staticassets/templatetags/__init__.py
staticassets/templatetags/staticassets.py