Metadata-Version: 1.1
Name: django-staticassets
Version: 0.1.2
Summary: Compiles and bundles static assets. Uses a directive processor similiar to Ruby's Sprockets
Home-page: https://github.com/davidelias/django-staticassets
Author: David Elias
Author-email: david@david-elias.net
License: MIT License
Platform: UNKNOWN
Classifier: Environment :: Web Environment
Classifier: Framework :: Django
Classifier: Intended Audience :: Developers
Classifier: License :: OSI Approved :: MIT License
Classifier: Operating System :: OS Independent
Classifier: Programming Language :: Python
Classifier: Programming Language :: Python :: 2.6
Classifier: Programming Language :: Python :: 2.7
Classifier: Topic :: Internet :: WWW/HTTP
Classifier: Topic :: Internet :: WWW/HTTP :: Dynamic Content
